gene_id_resolver/__init__.py
gene_id_resolver/cli/__init__.py
gene_id_resolver/cli/main.py
gene_id_resolver/core/__init__.py
gene_id_resolver/core/ambiguity.py
gene_id_resolver/core/database.py
gene_id_resolver/core/deprecated_genes.py
gene_id_resolver/core/models.py
gene_id_resolver/core/resolver.py
gene_id_resolver/core/resolver_enhanced.py
gene_id_resolver/core/species_detector.py
gene_id_resolver/core/updater.py
gene_id_resolver/core/versioning.py
gene_id_resolver/datasources/__init__.py
gene_id_resolver/datasources/ensembl.py
gene_id_resolver/utils/__init__.py
gene_id_resolver/utils/file_processor.py
gene_id_resolver/utils/file_processor_enhanced.py
gene_id_resolver-0.2.0.dist-info/licenses/LICENSE
gene_id_resolver-0.2.0.dist-info/METADATA
gene_id_resolver-0.2.0.dist-info/WHEEL
gene_id_resolver-0.2.0.dist-info/entry_points.txt
gene_id_resolver-0.2.0.dist-info/top_level.txt
gene_id_resolver-0.2.0.dist-info/RECORD
