Metadata-Version: 2.4
Name: gene-id-resolver
Version: 0.2.0
Summary: Production-grade gene ID conversion tool with multi-species support and auto-updates
Author-email: Taha Ahmad <tahagill99@gmail.com>
License-Expression: MIT
Project-URL: Homepage, https://github.com/tahagill/gene-id-resolver
Project-URL: Documentation, https://github.com/tahagill/gene-id-resolver#readme
Project-URL: Repository, https://github.com/tahagill/gene-id-resolver
Project-URL: Bug Reports, https://github.com/tahagill/gene-id-resolver/issues
Keywords: bioinformatics,genomics,gene-ids,ensembl,gene-conversion,hgnc,deprecated-genes
Classifier: Development Status :: 4 - Beta
Classifier: Intended Audience :: Science/Research
Classifier: Topic :: Scientific/Engineering :: Bio-Informatics
Classifier: Programming Language :: Python :: 3
Classifier: Programming Language :: Python :: 3.8
Classifier: Programming Language :: Python :: 3.9
Classifier: Programming Language :: Python :: 3.10
Classifier: Programming Language :: Python :: 3.11
Classifier: Programming Language :: Python :: 3.12
Requires-Python: >=3.8
License-File: LICENSE
Requires-Dist: pandas>=1.5.0
Requires-Dist: click>=8.1.0
Requires-Dist: tqdm>=4.64.0
Provides-Extra: dev
Requires-Dist: pytest>=7.0.0; extra == "dev"
Requires-Dist: pytest-cov; extra == "dev"
Requires-Dist: black>=22.0.0; extra == "dev"
Requires-Dist: flake8>=5.0.0; extra == "dev"
Dynamic: license-file
